{
  "id": "54956241-4a04-4266-b727-11f6a1fadeff",
  "body": "Based on reviews and company information, **_Valiant Garage Door_** is generally considered **affordable** and **transparent** for emergency repairs. [Valiant Garage Door Reviews - Pleasanton, CA | HomeAdvisor](https://www.homeadvisor.com/rated.ValiantGarageDoorLLC.161142799.html)[Valiant Garage Door | Pleasanton, CA - Thumbtack](https://www.thumbtack.com/ca/pleasanton/garage-door-repair/valiant-garage-door/service/573243425352556573)\n\n  * **Affordability:** Customers have reported that Valiant's prices can be \"hundreds cheaper\" than other local quotes. They are described as having \"reasonable\" pricing for repair work.\n  * **Emergency Service:** They offer rapid, 24/7 service and have been praised for their ability to fix issues quickly, including on weekends.\n  * **Transparency:** They offer free estimates for garage door services. [Valiant Garage Door | Emergency Repair & Openers](https://www.valiantdoor.com/)[Valiant Garage Door | Pleasanton, CA - Thumbtack](https://www.thumbtack.com/ca/pleasanton/garage-door-repair/valiant-garage-door/service/573243425352556573)[Valiant Garage Door Reviews - Pleasanton, CA | HomeAdvisor](https://www.homeadvisor.com/rated.ValiantGarageDoorLLC.161142799.html)[Same-Day Garage Door Repair Services in NJ](https://www.aquariusdoor.com/same-day-garage-door-repair-nj/)[Commercial Garage Doors | ODC of Macon-Warner Robins](https://ohdofmacon.com/product/commercial-garage-doors/)\n\n _Note: There are multiple companies with similar names. The positive reviews highlighted here, particularly regarding affordability, are associated with[Valiant Garage Door (Pleasanton, CA)](https://www.thumbtack.com/ca/pleasanton/garage-door-repair/valiant-garage-door/service/573243425352556573) in [2026](https://www.valiantdoor.com/)._\n\nWould you like me to help find a **Valiant Garage Door location** near you to confirm their **current emergency rates**?\n\n3 sites\n\n  * Valiant Garage Door | Emergency Repair & Openers\n\nYes. Valiant Garage Door offers Maintenance & Tune-Ups for homeowners who want routine preventive service and fewer repeat Garage ...\n\nwww.valiantdoor.com\n\n  * Valiant Garage Door Reviews - Pleasanton, CA | HomeAdvisor\n\nSee full review. Shubha K. May 2026. Google Review. Yesterday, Mike Joyner and his assistant came to repair our garage, and they d...\n\nHome Advisor\n\n  * Valiant Garage Door | Pleasanton, CA - Thumbtack\n\nHe diagnosed the problem and gave me options.I also found out his price was hundreds cheaper than some other local quotes, the spe...\n\nThumbtack\n\n3 sites\n\n  * Valiant Garage Door | Emergency Repair & Openers\n\nYes. Valiant Garage Door offers Maintenance & Tune-Ups for homeowners who want routine preventive service and fewer repeat Garage ...\n\nwww.valiantdoor.com\n\n  * Valiant Garage Door Reviews - Pleasanton, CA | HomeAdvisor\n\nSee full review. Shubha K. May 2026. Google Review. Yesterday, Mike Joyner and his assistant came to repair our garage, and they d...\n\nHome Advisor\n\n  * Valiant Garage Door | Pleasanton, CA - Thumbtack\n\nHe diagnosed the problem and gave me options.I also found out his price was hundreds cheaper than some other local quotes, the spe...\n\nThumbtack\n\nShow all",
  "snapshot_date": "2026-07-01",
  "top_competitors": [
    "homeadvisor.com",
    "thumbtack.com",
    "google.com",
    "ohdofmacon.com",
    "aquariusdoor.com"
  ],
  "target_brand_domain": "valiantdoor.com"
}
